<?xml version="1.0" encoding="UTF-8"?>
<metadata xml:lang="en"><Esri><CreaDate>20211201</CreaDate><CreaTime>04572100</CreaTime><ArcGISFormat>1.0</ArcGISFormat><SyncOnce>TRUE</SyncOnce><DataProperties><lineage><Process ToolSource="c:\program files\arcgis\pro\Resources\ArcToolbox\toolboxes\Data Management Tools.tbx\AddRelate" Date="20211201" Time="045721">AddRelate IND_adm1 NAME_1 AnnualTemperatureIndia States Relate1 "One to many"</Process><Process ToolSource="c:\program files\arcgis\pro\Resources\ArcToolbox\toolboxes\Data Management Tools.tbx\RemoveRelate" Date="20211201" Time="045747">RemoveRelate IND_adm1 Relate1</Process><Process ToolSource="c:\program files\arcgis\pro\Resources\ArcToolbox\toolboxes\Data Management Tools.tbx\DeleteField" Date="20211201" Time="045807">DeleteField IND_adm1 ISO</Process><Process ToolSource="c:\program files\arcgis\pro\Resources\ArcToolbox\toolboxes\Data Management Tools.tbx\DeleteField" Date="20211201" Time="045830">DeleteField IND_adm1 NAME_0</Process><Process ToolSource="c:\program files\arcgis\pro\Resources\ArcToolbox\toolboxes\Data Management Tools.tbx\DeleteField" Date="20211201" Time="045842">DeleteField IND_adm1 TYPE_1</Process><Process ToolSource="c:\program files\arcgis\pro\Resources\ArcToolbox\toolboxes\Data Management Tools.tbx\DeleteField" Date="20211201" Time="045848">DeleteField IND_adm1 NL_NAME_1</Process><Process ToolSource="c:\program files\arcgis\pro\Resources\ArcToolbox\toolboxes\Data Management Tools.tbx\DeleteField" Date="20211201" Time="045853">DeleteField IND_adm1 VARNAME_1</Process><Process ToolSource="c:\program files\arcgis\pro\Resources\ArcToolbox\toolboxes\Data Management Tools.tbx\AddRelate" Date="20211201" Time="053150">AddRelate IND_adm1 NAME_1 AnnualTemperatureIndia States Relate1 "One to many"</Process></lineage></DataProperties></Esri></metadata>
